sqlite_utils_llm/sqlite_utils_llm.py
sqlite_utils_llm-0.3.dist-info/METADATA
sqlite_utils_llm-0.3.dist-info/WHEEL
sqlite_utils_llm-0.3.dist-info/entry_points.txt
sqlite_utils_llm-0.3.dist-info/top_level.txt
sqlite_utils_llm-0.3.dist-info/RECORD
