Metadata-Version: 2.4
Name: sqlite-utils-llm
Version: 0.3
Summary: Run llm from sqlite
Author: Brian J. Cardiff
License-Expression: MIT
Project-URL: Homepage, https://github.com/bcardiff/sqlite-utils-llm
Project-URL: Changelog, https://github.com/bcardiff/sqlite-utils-llm/releases
Project-URL: Issues, https://github.com/bcardiff/sqlite-utils-llm/issues
Project-URL: CI, https://github.com/bcardiff/sqlite-utils-llm/actions
Classifier: Topic :: Database
Classifier: Environment :: Plugins
Requires-Dist: sqlite-utils
